lowbudget2gocli.py
lowbudget_2go_cli-0.1.0.dist-info/entry_points.txt
lowbudget_2go_cli-0.1.0.dist-info/WHEEL
lowbudget_2go_cli-0.1.0.dist-info/METADATA
lowbudget_2go_cli-0.1.0.dist-info/RECORD
