Metadata-Version: 2.1
Name: lowbudget-2go-cli
Version: 0.1.0
Summary: A command line application that allows developers post, read, comment and like gossips
Author: Adeayo
Requires-Python: >3.0
Classifier: Programming Language :: Python :: 3
Classifier: Programming Language :: Python :: 3.4
Classifier: Programming Language :: Python :: 3.5
Classifier: Programming Language :: Python :: 3.6
Classifier: Programming Language :: Python :: 3.7
Classifier: Programming Language :: Python :: 3.8
